{
  "dungeontactics:recipes/misc/convenience/planks_from_sticks": {
    "criteria": {
      "has_acacia": "2024-12-26 07:03:21 +0000"
    },
    "done": true
  },
  "minecraft:recipes/decorations/purple_stained_glass_pane": {
    "criteria": {
      "has_glass": "2024-12-26 07:09:36 +0000"
    },
    "done": true
  },
  "dungeontactics:recipes/weapons/stone_weapons": {
    "criteria": {
      "has_item": "2024-12-26 07:06:01 +0000"
    },
    "done": true
  },
  "minecraft:recipes/building_blocks/black_stained_glass": {
    "criteria": {
      "has_glass": "2024-12-26 07:09:36 +0000"
    },
    "done": true
  },
  "minecraft:recipes/building_blocks/purple_wool": {
    "criteria": {
      "has_white_wool": "2024-12-26 07:19:32 +0000"
    },
    "done": true
  },
  "minecraft:recipes/tools/wooden_axe": {
    "criteria": {
      "has_stick": "2024-12-26 07:03:23 +0000"
    },
    "done": true
  },
  "minecraft:recipes/building_blocks/lime_wool": {
    "criteria": {
      "has_white_wool": "2024-12-26 07:19:32 +0000"
    },
    "done": true
  },
  "minecraft:recipes/redstone/lever": {
    "criteria": {
      "has_cobblestone": "2024-12-26 07:06:01 +0000"
    },
    "done": true
  },
  "minecraft:recipes/building_blocks/acacia_wooden_slab": {
    "criteria": {
      "has_planks": "2024-12-26 07:03:21 +0000"
    },
    "done": true
  },
  "minecraft:recipes/building_blocks/black_wool": {
    "criteria": {
      "has_white_wool": "2024-12-26 07:19:32 +0000"
    },
    "done": true
  },
  "minecraft:recipes/misc/writable_book": {
    "criteria": {
      "has_book": "2024-12-26 07:12:49 +0000"
    },
    "done": true
  },
  "minecraft:recipes/building_blocks/oak_wooden_slab": {
    "criteria": {
      "has_planks": "2024-12-26 07:05:38 +0000"
    },
    "done": true
  },
  "dungeontactics:recipes/misc/convenience/sticks_from_cactus": {
    "criteria": {
      "has_stick": "2024-12-26 07:03:23 +0000"
    },
    "done": true
  },
  "minecraft:recipes/decorations/white_bed": {
    "criteria": {
      "has_white_wool": "2024-12-26 07:19:32 +0000"
    },
    "done": true
  },
  "minecraft:recipes/building_blocks/green_wool": {
    "criteria": {
      "has_white_wool": "2024-12-26 07:19:32 +0000"
    },
    "done": true
  },
  "minecraft:recipes/building_blocks/gray_stained_glass": {
    "criteria": {
      "has_glass": "2024-12-26 07:09:36 +0000"
    },
    "done": true
  },
  "minecraft:recipes/brewing/glass_bottle": {
    "criteria": {
      "has_glass": "2024-12-26 07:09:36 +0000"
    },
    "done": true
  },
  "minecraft:recipes/building_blocks/brown_wool": {
    "criteria": {
      "has_white_wool": "2024-12-26 07:19:32 +0000"
    },
    "done": true
  },
  "dungeontactics:recipes/misc/convenience/melonslice_from_melon": {
    "criteria": {
      "has_melon": "2024-12-26 07:07:22 +0000"
    },
    "done": true
  },
  "minecraft:recipes/building_blocks/magenta_wool": {
    "criteria": {
      "has_white_wool": "2024-12-26 07:19:32 +0000"
    },
    "done": true
  },
  "minecraft:recipes/decorations/crafting_table": {
    "criteria": {
      "has_planks": "2024-12-26 07:03:21 +0000"
    },
    "done": true
  },
  "minecraft:recipes/decorations/light_blue_stained_glass_pane": {
    "criteria": {
      "has_glass": "2024-12-26 07:09:36 +0000"
    },
    "done": true
  },
  "minecraft:recipes/building_blocks/purple_stained_glass": {
    "criteria": {
      "has_glass": "2024-12-26 07:09:36 +0000"
    },
    "done": true
  },
  "minecraft:recipes/misc/melon_seeds": {
    "criteria": {
      "has_melon": "2024-12-26 07:07:22 +0000"
    },
    "done": true
  },
  "minecraft:recipes/redstone/trapdoor": {
    "criteria": {
      "has_planks": "2024-12-26 07:03:21 +0000"
    },
    "done": true
  },
  "iceandfire:iceandfire/root": {
    "criteria": {
      "tick": "2024-12-26 06:52:30 +0000"
    },
    "done": true
  },
  "minecraft:recipes/decorations/ladder": {
    "criteria": {
      "has_stick": "2024-12-26 07:03:23 +0000"
    },
    "done": true
  },
  "minecraft:recipes/decorations/lime_stained_glass_pane": {
    "criteria": {
      "has_glass": "2024-12-26 07:09:36 +0000"
    },
    "done": true
  },
  "dungeontactics:recipes/misc/cushions": {
    "criteria": {
      "has_recipe": "2024-12-26 07:19:32 +0000"
    },
    "done": true
  },
  "minecraft:recipes/decorations/chest": {
    "criteria": {
      "has_lots_of_items": "2024-12-26 07:03:58 +0000"
    },
    "done": true
  },
  "minecraft:recipes/decorations/magenta_stained_glass_pane": {
    "criteria": {
      "has_glass": "2024-12-26 07:09:36 +0000"
    },
    "done": true
  },
  "minecraft:recipes/decorations/painting": {
    "criteria": {
      "has_wool": "2024-12-26 07:19:32 +0000"
    },
    "done": true
  },
  "minecraft:recipes/building_blocks/white_stained_glass": {
    "criteria": {
      "has_glass": "2024-12-26 07:09:36 +0000"
    },
    "done": true
  },
  "minecraft:recipes/tools/wooden_shovel": {
    "criteria": {
      "has_stick": "2024-12-26 07:03:23 +0000"
    },
    "done": true
  },
  "dungeontactics:recipes/misc/wooden_chair": {
    "criteria": {
      "has_wood": "2024-12-26 07:03:23 +0000"
    },
    "done": true
  },
  "minecraft:recipes/decorations/torch": {
    "criteria": {
      "has_stone_pickaxe": "2024-12-26 07:07:08 +0000"
    },
    "done": true
  },
  "minecraft:recipes/decorations/cyan_stained_glass_pane": {
    "criteria": {
      "has_glass": "2024-12-26 07:09:36 +0000"
    },
    "done": true
  },
  "minecraft:recipes/redstone/wooden_pressure_plate": {
    "criteria": {
      "has_planks": "2024-12-26 07:03:21 +0000"
    },
    "done": true
  },
  "minecraft:recipes/building_blocks/blue_stained_glass": {
    "criteria": {
      "has_glass": "2024-12-26 07:09:36 +0000"
    },
    "done": true
  },
  "minecraft:recipes/building_blocks/cyan_wool": {
    "criteria": {
      "has_white_wool": "2024-12-26 07:19:32 +0000"
    },
    "done": true
  },
  "minecraft:recipes/combat/arrow": {
    "criteria": {
      "has_feather": "2024-12-26 07:11:53 +0000"
    },
    "done": true
  },
  "minecraft:recipes/misc/stick": {
    "criteria": {
      "has_planks": "2024-12-26 07:03:21 +0000"
    },
    "done": true
  },
  "minecraft:recipes/redstone/acacia_fence_gate": {
    "criteria": {
      "has_planks": "2024-12-26 07:03:21 +0000"
    },
    "done": true
  },
  "minecraft:recipes/building_blocks/coal_block": {
    "criteria": {
      "has_at_least_9_coal": "2024-12-26 07:08:52 +0000"
    },
    "done": true
  },
  "dungeontactics:recipes/misc/wooden_table": {
    "criteria": {
      "has_recipe": "2024-12-26 07:03:23 +0000",
      "has_wood": "2024-12-26 07:03:23 +0000"
    },
    "done": true
  },
  "minecraft:recipes/decorations/sign": {
    "criteria": {
      "has_planks": "2024-12-26 07:03:21 +0000"
    },
    "done": true
  },
  "minecraft:recipes/building_blocks/green_stained_glass": {
    "criteria": {
      "has_glass": "2024-12-26 07:09:36 +0000"
    },
    "done": true
  },
  "minecraft:recipes/transportation/spruce_boat": {
    "criteria": {
      "entered_water": "2024-12-26 07:02:41 +0000"
    },
    "done": true
  },
  "dungeontactics:recipes/tools/magic_tether": {
    "criteria": {
      "has_pearl": "2024-12-26 07:11:36 +0000"
    },
    "done": true
  },
  "minecraft:recipes/building_blocks/light_blue_wool": {
    "criteria": {
      "has_white_wool": "2024-12-26 07:19:32 +0000"
    },
    "done": true
  },
  "minecraft:recipes/tools/flint_and_steel": {
    "criteria": {
      "has_obsidian": "2024-12-26 07:11:57 +0000"
    },
    "done": true
  },
  "minecraft:recipes/redstone/wooden_button": {
    "criteria": {
      "has_planks": "2024-12-26 07:03:21 +0000"
    },
    "done": true
  },
  "minecraft:recipes/combat/wooden_sword": {
    "criteria": {
      "has_stick": "2024-12-26 07:03:23 +0000"
    },
    "done": true
  },
  "minecraft:recipes/tools/stone_shovel": {
    "criteria": {
      "has_cobblestone": "2024-12-26 07:06:01 +0000"
    },
    "done": true
  },
  "minecraft:recipes/decorations/yellow_stained_glass_pane": {
    "criteria": {
      "has_glass": "2024-12-26 07:09:36 +0000"
    },
    "done": true
  },
  "minecraft:recipes/building_blocks/oak_planks": {
    "criteria": {
      "has_log": "2024-12-26 07:04:13 +0000"
    },
    "done": true
  },
  "minecraft:recipes/building_blocks/cyan_stained_glass": {
    "criteria": {
      "has_glass": "2024-12-26 07:09:36 +0000"
    },
    "done": true
  },
  "dungeontactics:recipes/misc/convenience/string_from_wool": {
    "criteria": {
      "has_wool": "2024-12-26 07:19:32 +0000"
    },
    "done": true
  },
  "minecraft:recipes/building_blocks/gray_wool": {
    "criteria": {
      "has_white_wool": "2024-12-26 07:19:32 +0000"
    },
    "done": true
  },
  "minecraft:recipes/building_blocks/bookshelf": {
    "criteria": {
      "has_book": "2024-12-26 07:12:49 +0000"
    },
    "done": true
  },
  "minecraft:recipes/decorations/fence": {
    "criteria": {
      "has_planks": "2024-12-26 07:05:38 +0000"
    },
    "done": true
  },
  "dungeontactics:recipes/tools/climbing_rope": {
    "criteria": {
      "has_recipe": "2024-12-26 07:03:23 +0000"
    },
    "done": true
  },
  "minecraft:recipes/redstone/dark_oak_door": {
    "criteria": {
      "has_planks": "2024-12-26 07:14:03 +0000"
    },
    "done": true
  },
  "minecraft:husbandry/balanced_diet": {
    "criteria": {
      "melon": "2024-12-26 07:16:54 +0000",
      "bread": "2024-12-26 07:09:48 +0000"
    },
    "done": false
  },
  "minecraft:recipes/tools/wooden_hoe": {
    "criteria": {
      "has_stick": "2024-12-26 07:03:23 +0000"
    },
    "done": true
  },
  "minecraft:recipes/building_blocks/cobblestone_slab": {
    "criteria": {
      "has_cobblestone": "2024-12-26 07:06:01 +0000"
    },
    "done": true
  },
  "minecraft:recipes/building_blocks/dark_oak_wooden_slab": {
    "criteria": {
      "has_planks": "2024-12-26 07:14:03 +0000"
    },
    "done": true
  },
  "minecraft:recipes/brewing/speckled_melon": {
    "criteria": {
      "has_melon": "2024-12-26 07:07:22 +0000"
    },
    "done": true
  },
  "minecraft:story/iron_tools": {
    "criteria": {
      "iron_pickaxe": "2024-12-26 07:21:39 +0000"
    },
    "done": true
  },
  "minecraft:recipes/decorations/orange_stained_glass_pane": {
    "criteria": {
      "has_glass": "2024-12-26 07:09:36 +0000"
    },
    "done": true
  },
  "minecraft:recipes/redstone/fence_gate": {
    "criteria": {
      "has_planks": "2024-12-26 07:05:38 +0000"
    },
    "done": true
  },
  "minecraft:story/root": {
    "criteria": {
      "crafting_table": "2024-12-26 07:03:23 +0000"
    },
    "done": true
  },
  "minecraft:recipes/decorations/white_banner": {
    "criteria": {
      "has_white_wool": "2024-12-26 07:19:32 +0000"
    },
    "done": true
  },
  "dungeontactics:dungeoneering/born_survivor": {
    "criteria": {
      "stab": "2024-12-26 06:52:30 +0000",
      "cherrybomb": "2024-12-26 07:04:48 +0000",
      "heart": "2024-12-26 07:11:36 +0000"
    },
    "done": false
  },
  "minecraft:recipes/building_blocks/yellow_wool": {
    "criteria": {
      "has_white_wool": "2024-12-26 07:19:32 +0000"
    },
    "done": true
  },
  "minecraft:recipes/misc/coal": {
    "criteria": {
      "has_the_recipe": "2024-12-26 07:08:52 +0000"
    },
    "done": true
  },
  "dungeontactics:recipes/weapons/wooden_weapons": {
    "criteria": {
      "has_item": "2024-12-26 07:03:23 +0000"
    },
    "done": true
  },
  "minecraft:story/form_obsidian": {
    "criteria": {
      "obsidian": "2024-12-26 07:11:57 +0000"
    },
    "done": true
  },
  "dungeontactics:dungeoneering/root": {
    "criteria": {
      "kill": "2024-12-26 07:10:36 +0000"
    },
    "done": true
  },
  "dungeontactics:recipes/tools/fire_starter": {
    "criteria": {
      "has_item": "2024-12-26 07:03:23 +0000"
    },
    "done": true
  },
  "inventorypets:inventorypets/root": {
    "criteria": {
      "auto": "2024-12-26 06:52:30 +0000"
    },
    "done": true
  },
  "tombstone:tutorial/root": {
    "criteria": {
      "auto": "2024-12-26 06:52:30 +0000"
    },
    "done": true
  },
  "dungeontactics:recipes/misc/dungeonpedia": {
    "criteria": {
      "has_book": "2024-12-26 07:12:49 +0000"
    },
    "done": true
  },
  "minecraft:recipes/decorations/black_stained_glass_pane": {
    "criteria": {
      "has_glass": "2024-12-26 07:09:36 +0000"
    },
    "done": true
  },
  "dungeontactics:recipes/misc/obsidianbrick": {
    "criteria": {
      "has_item": "2024-12-26 07:11:57 +0000"
    },
    "done": true
  },
  "minecraft:recipes/building_blocks/acacia_planks": {
    "criteria": {
      "has_log2": "2024-12-26 07:03:15 +0000"
    },
    "done": true
  },
  "minecraft:recipes/building_blocks/yellow_stained_glass": {
    "criteria": {
      "has_glass": "2024-12-26 07:09:36 +0000"
    },
    "done": true
  },
  "minecraft:recipes/decorations/acacia_fence": {
    "criteria": {
      "has_planks": "2024-12-26 07:03:21 +0000"
    },
    "done": true
  },
  "minecraft:adventure/kill_a_mob": {
    "criteria": {
      "zombie": "2024-12-26 07:14:35 +0000"
    },
    "done": true
  },
  "minecraft:recipes/building_blocks/blue_wool": {
    "criteria": {
      "has_white_wool": "2024-12-26 07:19:32 +0000"
    },
    "done": true
  },
  "minecraft:story/obtain_armor": {
    "criteria": {
      "iron_leggings": "2024-12-26 07:11:57 +0000"
    },
    "done": true
  },
  "minecraft:story/mine_stone": {
    "criteria": {
      "get_stone": "2024-12-26 07:06:01 +0000"
    },
    "done": true
  },
  "dungeontactics:recipes/misc/brazier": {
    "criteria": {
      "has_torch": "2024-12-26 07:08:22 +0000"
    },
    "done": true
  },
  "dungeontactics:recipes/misc/lantern_iron": {
    "criteria": {
      "has_torch": "2024-12-26 07:08:22 +0000"
    },
    "done": true
  },
  "minecraft:recipes/decorations/furnace": {
    "criteria": {
      "has_cobblestone": "2024-12-26 07:06:01 +0000"
    },
    "done": true
  },
  "minecraft:adventure/adventuring_time": {
    "criteria": {
      "beaches": "2024-12-26 07:02:35 +0000",
      "savanna": "2024-12-26 07:02:45 +0000",
      "savanna_rock": "2024-12-26 06:52:30 +0000",
      "ocean": "2024-12-26 07:11:07 +0000",
      "river": "2024-12-26 07:02:41 +0000"
    },
    "done": false
  },
  "minecraft:recipes/decorations/gray_stained_glass_pane": {
    "criteria": {
      "has_glass": "2024-12-26 07:09:36 +0000"
    },
    "done": true
  },
  "minecraft:recipes/building_blocks/red_stained_glass": {
    "criteria": {
      "has_glass": "2024-12-26 07:09:36 +0000"
    },
    "done": true
  },
  "minecraft:recipes/decorations/green_stained_glass_pane": {
    "criteria": {
      "has_glass": "2024-12-26 07:09:36 +0000"
    },
    "done": true
  },
  "minecraft:recipes/building_blocks/orange_wool": {
    "criteria": {
      "has_white_wool": "2024-12-26 07:19:32 +0000"
    },
    "done": true
  },
  "minecraft:recipes/tools/wooden_pickaxe": {
    "criteria": {
      "has_stick": "2024-12-26 07:03:23 +0000"
    },
    "done": true
  },
  "dungeontactics:recipes/tools/flint_and_steel": {
    "criteria": {
      "has_obsidian": "2024-12-26 07:11:57 +0000"
    },
    "done": true
  },
  "minecraft:husbandry/root": {
    "criteria": {
      "consumed_item": "2024-12-26 07:04:48 +0000"
    },
    "done": true
  },
  "minecraft:recipes/transportation/birch_boat": {
    "criteria": {
      "entered_water": "2024-12-26 07:02:41 +0000"
    },
    "done": true
  },
  "minecraft:recipes/combat/stone_sword": {
    "criteria": {
      "has_cobblestone": "2024-12-26 07:06:01 +0000"
    },
    "done": true
  },
  "minecraft:recipes/building_blocks/oak_stairs": {
    "criteria": {
      "has_planks": "2024-12-26 07:05:38 +0000"
    },
    "done": true
  },
  "minecraft:recipes/decorations/cobblestone_wall": {
    "criteria": {
      "has_cobblestone": "2024-12-26 07:06:01 +0000"
    },
    "done": true
  },
  "cfm:install": {
    "criteria": {
      "tick": "2024-12-26 06:52:30 +0000"
    },
    "done": true
  },
  "minecraft:recipes/decorations/enchanting_table": {
    "criteria": {
      "has_obsidian": "2024-12-26 07:11:57 +0000"
    },
    "done": true
  },
  "minecraft:recipes/transportation/acacia_boat": {
    "criteria": {
      "entered_water": "2024-12-26 07:02:41 +0000"
    },
    "done": true
  },
  "minecraft:recipes/tools/stone_pickaxe": {
    "criteria": {
      "has_cobblestone": "2024-12-26 07:06:01 +0000"
    },
    "done": true
  },
  "minecraft:recipes/redstone/acacia_door": {
    "criteria": {
      "has_planks": "2024-12-26 07:03:21 +0000"
    },
    "done": true
  },
  "minecraft:recipes/building_blocks/orange_stained_glass": {
    "criteria": {
      "has_glass": "2024-12-26 07:09:36 +0000"
    },
    "done": true
  },
  "minecraft:recipes/building_blocks/brown_stained_glass": {
    "criteria": {
      "has_glass": "2024-12-26 07:09:36 +0000"
    },
    "done": true
  },
  "minecraft:adventure/root": {
    "criteria": {
      "killed_something": "2024-12-26 07:10:36 +0000"
    },
    "done": true
  },
  "minecraft:recipes/transportation/boat": {
    "criteria": {
      "entered_water": "2024-12-26 07:02:41 +0000"
    },
    "done": true
  },
  "minecraft:recipes/transportation/jungle_boat": {
    "criteria": {
      "entered_water": "2024-12-26 07:02:41 +0000"
    },
    "done": true
  },
  "dungeontactics:recipes/misc/convenience/sticks_from_saplings": {
    "criteria": {
      "has_stick": "2024-12-26 07:03:23 +0000"
    },
    "done": true
  },
  "minecraft:recipes/building_blocks/light_gray_stained_glass": {
    "criteria": {
      "has_glass": "2024-12-26 07:09:36 +0000"
    },
    "done": true
  },
  "dungeontactics:recipes/misc/convenience/books_from_shelves": {
    "criteria": {
      "has_book": "2024-12-26 07:12:49 +0000"
    },
    "done": true
  },
  "minecraft:recipes/tools/stone_hoe": {
    "criteria": {
      "has_cobblestone": "2024-12-26 07:06:01 +0000"
    },
    "done": true
  },
  "minecraft:recipes/transportation/dark_oak_boat": {
    "criteria": {
      "entered_water": "2024-12-26 07:02:41 +0000"
    },
    "done": true
  },
  "minecraft:recipes/building_blocks/pink_wool": {
    "criteria": {
      "has_white_wool": "2024-12-26 07:19:32 +0000"
    },
    "done": true
  },
  "minecraft:recipes/decorations/red_stained_glass_pane": {
    "criteria": {
      "has_glass": "2024-12-26 07:09:36 +0000"
    },
    "done": true
  },
  "minecraft:recipes/decorations/white_stained_glass_pane": {
    "criteria": {
      "has_glass": "2024-12-26 07:09:36 +0000"
    },
    "done": true
  },
  "minecraft:adventure/kill_all_mobs": {
    "criteria": {
      "skeleton": "2024-12-26 07:14:54 +0000",
      "silverfish": "2024-12-26 07:20:46 +0000",
      "zombie": "2024-12-26 07:14:35 +0000"
    },
    "done": false
  },
  "minecraft:recipes/building_blocks/dark_oak_stairs": {
    "criteria": {
      "has_planks": "2024-12-26 07:14:03 +0000"
    },
    "done": true
  },
  "dungeontactics:dungeoneering/get_lootbag": {
    "criteria": {
      "quiver": "2024-12-26 07:15:30 +0000"
    },
    "done": true
  },
  "advancedrocketry:normal/root": {
    "criteria": {
      "crafting_table": "2024-12-26 07:03:23 +0000"
    },
    "done": true
  },
  "minecraft:recipes/building_blocks/lime_stained_glass": {
    "criteria": {
      "has_glass": "2024-12-26 07:09:36 +0000"
    },
    "done": true
  },
  "minecraft:recipes/building_blocks/melon_block": {
    "criteria": {
      "has_melon": "2024-12-26 07:07:22 +0000"
    },
    "done": true
  },
  "minecraft:recipes/decorations/white_carpet": {
    "criteria": {
      "has_white_wool": "2024-12-26 07:19:32 +0000"
    },
    "done": true
  },
  "minecraft:recipes/decorations/pink_stained_glass_pane": {
    "criteria": {
      "has_glass": "2024-12-26 07:09:36 +0000"
    },
    "done": true
  },
  "dungeontactics:recipes/armour/stone_plate_armour": {
    "criteria": {
      "has_item": "2024-12-26 07:06:01 +0000"
    },
    "done": true
  },
  "minecraft:recipes/redstone/dark_oak_fence_gate": {
    "criteria": {
      "has_planks": "2024-12-26 07:14:03 +0000"
    },
    "done": true
  },
  "minecraft:recipes/building_blocks/stone_stairs": {
    "criteria": {
      "has_cobblestone": "2024-12-26 07:06:01 +0000"
    },
    "done": true
  },
  "cfm:root": {
    "criteria": {
      "tick": "2024-12-26 06:52:30 +0000"
    },
    "done": true
  },
  "minecraft:recipes/decorations/glass_pane": {
    "criteria": {
      "has_glass": "2024-12-26 07:09:36 +0000"
    },
    "done": true
  },
  "minecraft:recipes/decorations/brown_stained_glass_pane": {
    "criteria": {
      "has_glass": "2024-12-26 07:09:36 +0000"
    },
    "done": true
  },
  "fossil:fossil/root": {
    "criteria": {
      "tick": "2024-12-26 06:52:30 +0000"
    },
    "done": true
  },
  "minecraft:recipes/decorations/dark_oak_fence": {
    "criteria": {
      "has_planks": "2024-12-26 07:14:03 +0000"
    },
    "done": true
  },
  "minecraft:recipes/building_blocks/magenta_stained_glass": {
    "criteria": {
      "has_glass": "2024-12-26 07:09:36 +0000"
    },
    "done": true
  },
  "minecraft:story/upgrade_tools": {
    "criteria": {
      "stone_pickaxe": "2024-12-26 07:07:08 +0000"
    },
    "done": true
  },
  "minecraft:recipes/building_blocks/light_gray_wool": {
    "criteria": {
      "has_white_wool": "2024-12-26 07:19:32 +0000"
    },
    "done": true
  },
  "minecraft:recipes/building_blocks/red_wool": {
    "criteria": {
      "has_white_wool": "2024-12-26 07:19:32 +0000"
    },
    "done": true
  },
  "minecraft:recipes/building_blocks/acacia_stairs": {
    "criteria": {
      "has_planks": "2024-12-26 07:03:21 +0000"
    },
    "done": true
  },
  "minecraft:recipes/tools/stone_axe": {
    "criteria": {
      "has_cobblestone": "2024-12-26 07:06:01 +0000"
    },
    "done": true
  },
  "minecraft:recipes/building_blocks/light_blue_stained_glass": {
    "criteria": {
      "has_glass": "2024-12-26 07:09:36 +0000"
    },
    "done": true
  },
  "minecraft:recipes/redstone/wooden_door": {
    "criteria": {
      "has_planks": "2024-12-26 07:05:38 +0000"
    },
    "done": true
  },
  "dungeontactics:recipes/misc/barrel": {
    "criteria": {
      "has_acacia": "2024-12-26 07:03:21 +0000"
    },
    "done": true
  },
  "minecraft:recipes/building_blocks/pink_stained_glass": {
    "criteria": {
      "has_glass": "2024-12-26 07:09:36 +0000"
    },
    "done": true
  },
  "minecraft:recipes/decorations/blue_stained_glass_pane": {
    "criteria": {
      "has_glass": "2024-12-26 07:09:36 +0000"
    },
    "done": true
  },
  "minecraft:recipes/decorations/light_gray_stained_glass_pane": {
    "criteria": {
      "has_glass": "2024-12-26 07:09:36 +0000"
    },
    "done": true
  }
}